adfp/__init__.py
adfp/analytic_function.py
adfp/calc_utils.py
adfp/config.py
adfp/function.py
adfp/module_config.py
adfp/utils.py
adfp/core/__init__.py
adfp/core/arithmetic_operator.py
adfp/core/variable.py
adfp/core_simple/__init__.py
adfp/core_simple/arithmetic_operator.py
adfp/core_simple/variable.py
adfp-0.0.1.dist-info/LICENSE
adfp-0.0.1.dist-info/METADATA
adfp-0.0.1.dist-info/WHEEL
adfp-0.0.1.dist-info/top_level.txt
adfp-0.0.1.dist-info/RECORD
