Metadata-Version: 2.1
Name: adfp
Version: 0.0.1
Summary: auto differential framework
Home-page: https://github.com/enoTak/adfp
Author: Takumi Enomoto
Author-email: eno.sleepy.zzz.zz.z@gmail.com
License: MIT License
Keywords: auto differential
License-File: LICENSE
Requires-Dist: numpy
